mlrose/__init__.py
mlrose/activation.py
mlrose/algorithms.py
mlrose/decay.py
mlrose/fitness.py
mlrose/neural.py
mlrose/opt_probs.py
mlrose-1.3.0.dist-info/LICENSE
mlrose-1.3.0.dist-info/METADATA
mlrose-1.3.0.dist-info/WHEEL
mlrose-1.3.0.dist-info/top_level.txt
mlrose-1.3.0.dist-info/RECORD
